is_propchecker/__init__.py
is_propchecker/__main__.py
is_propchecker/main.py
is_propchecker-0.1.0.dist-info/METADATA
is_propchecker-0.1.0.dist-info/WHEEL
is_propchecker-0.1.0.dist-info/entry_points.txt
is_propchecker-0.1.0.dist-info/RECORD
